sung/__init__.py
sung/base.py
sung/chords_and_lyrics.py
sung/pydantic_models.py
sung/tools.py
sung/util.py
sung-0.0.23.dist-info/licenses/LICENSE
sung-0.0.23.dist-info/METADATA
sung-0.0.23.dist-info/WHEEL
sung-0.0.23.dist-info/top_level.txt
sung-0.0.23.dist-info/RECORD
