Metadata-Version: 2.4
Name: sung
Version: 0.0.23
Summary: Music data access
Home-page: https://github.com/thorwhalen/sung
Author: Thor Whalen
License: mit
Platform: any
License-File: LICENSE
Requires-Dist: spotipy
Requires-Dist: tabled
Requires-Dist: glom
Requires-Dist: i2
Requires-Dist: pydantic
Requires-Dist: pandas
Requires-Dist: requests
Requires-Dist: reportlab
Dynamic: license-file
